odp2md/__init__.py
odp2md/__main__.py
odp2md/odp2md.py
odp2md-0.3.3.dist-info/LICENSE.md
odp2md-0.3.3.dist-info/METADATA
odp2md-0.3.3.dist-info/WHEEL
odp2md-0.3.3.dist-info/entry_points.txt
odp2md-0.3.3.dist-info/top_level.txt
odp2md-0.3.3.dist-info/RECORD
