Metadata-Version: 2.1
Name: odp2md
Version: 0.3.3
Summary: convert OpenOffice odp to markdown
Home-page: https://github.com/seichter/odp2md
Author: Hartmut Seichter
Author-email: hartmut@technotecture.com
License: UNKNOWN
Platform: UNKNOWN
Classifier: Programming Language :: Python :: 3
Classifier: License :: OSI Approved :: GNU General Public License v3 (GPLv3)
Classifier: Operating System :: OS Independent
Requires-Python: >=3.6
License-File: LICENSE.md
